setup.py
page/__init__.py
page/admin.py
page/apps.py
page/middleware.py
page/models.py
page/tests.py
page/views.py
page/migrations/0001_initial.py
page/migrations/__init__.py
pageViewCount.egg-info/PKG-INFO
pageViewCount.egg-info/SOURCES.txt
pageViewCount.egg-info/dependency_links.txt
pageViewCount.egg-info/requires.txt
pageViewCount.egg-info/top_level.txt