Metadata-Version: 1.0
Name: pageViewCount
Version: 0.1.2
Summary: Statistics page number of views 
Home-page: https://github.com/Fiz1994/pageViewCount
Author: FizLin
Author-email: fizlbq@gamil.com
License: UNKNOWN
Platform: UNKNOWN
